mmaare.py
python_mmaare-0.3.dist-info/METADATA
python_mmaare-0.3.dist-info/WHEEL
python_mmaare-0.3.dist-info/historia.json
python_mmaare-0.3.dist-info/top_level.txt
python_mmaare-0.3.dist-info/RECORD
