Metadata-Version: 2.4
Name: python-mmaare
Version: 0.3
Summary: Python-moduulimääretoteutus
Author-email: Antti Hautaniemi <antti.hautaniemi@pispalanit.fi>
Project-URL: Repository, https://github.com/an7oine/python-mmaare.git
Requires-Python: >=3.8
